ffmpeg/__init__.py
ffmpeg/_version.py
ffmpeg/base.py
ffmpeg/exceptions.py
ffmpeg/expressions.py
ffmpeg/filters.py
ffmpeg/info.py
ffmpeg/py.typed
ffmpeg/schema.py
ffmpeg/sources.py
ffmpeg/types.py
ffmpeg/codecs/__init__.py
ffmpeg/codecs/decoders.py
ffmpeg/codecs/encoders.py
ffmpeg/codecs/schema.py
ffmpeg/common/__init__.py
ffmpeg/common/cache.py
ffmpeg/common/schema.py
ffmpeg/common/serialize.py
ffmpeg/common/cache/FFMpegFilterManuallyDefined/acrossover.json
ffmpeg/common/cache/FFMpegFilterManuallyDefined/afir.json
ffmpeg/common/cache/FFMpegFilterManuallyDefined/aiir.json
ffmpeg/common/cache/FFMpegFilterManuallyDefined/ainterleave.json
ffmpeg/common/cache/FFMpegFilterManuallyDefined/amerge.json
ffmpeg/common/cache/FFMpegFilterManuallyDefined/amix.json
ffmpeg/common/cache/FFMpegFilterManuallyDefined/amovie.json
ffmpeg/common/cache/FFMpegFilterManuallyDefined/anequalizer.json
ffmpeg/common/cache/FFMpegFilterManuallyDefined/aphasemeter.json
ffmpeg/common/cache/FFMpegFilterManuallyDefined/asegment.json
ffmpeg/common/cache/FFMpegFilterManuallyDefined/aselect.json
ffmpeg/common/cache/FFMpegFilterManuallyDefined/asplit.json
ffmpeg/common/cache/FFMpegFilterManuallyDefined/astreamselect.json
ffmpeg/common/cache/FFMpegFilterManuallyDefined/bm3d.json
ffmpeg/common/cache/FFMpegFilterManuallyDefined/channelsplit.json
ffmpeg/common/cache/FFMpegFilterManuallyDefined/concat.json
ffmpeg/common/cache/FFMpegFilterManuallyDefined/decimate.json
ffmpeg/common/cache/FFMpegFilterManuallyDefined/ebur128.json
ffmpeg/common/cache/FFMpegFilterManuallyDefined/extractplanes.json
ffmpeg/common/cache/FFMpegFilterManuallyDefined/fieldmatch.json
ffmpeg/common/cache/FFMpegFilterManuallyDefined/guided.json
ffmpeg/common/cache/FFMpegFilterManuallyDefined/headphone.json
ffmpeg/common/cache/FFMpegFilterManuallyDefined/hstack.json
ffmpeg/common/cache/FFMpegFilterManuallyDefined/hstack_vaapi.json
ffmpeg/common/cache/FFMpegFilterManuallyDefined/interleave.json
typed_ffmpeg-3.11.dist-info/licenses/LICENSE
typed_ffmpeg-3.11.dist-info/METADATA
typed_ffmpeg-3.11.dist-info/WHEEL
typed_ffmpeg-3.11.dist-info/entry_points.txt
typed_ffmpeg-3.11.dist-info/top_level.txt
typed_ffmpeg-3.11.dist-info/RECORD
