Metadata-Version: 2.4
Name: typed-ffmpeg
Version: 3.11
Summary: Modern Python FFmpeg wrappers offer comprehensive support for complex filters, complete with detailed typing and documentation.
Author-email: lucemia <lucemia@gmail.com>
License-Expression: MIT
Project-URL: Homepage, https://livingbio.github.io/typed-ffmpeg/
Project-URL: Repository, https://github.com/livingbio/typed-ffmpeg
Keywords: ffmpeg,video,audio,multimedia,filter
Classifier: Intended Audience :: Developers
Classifier: Natural Language :: English
Classifier: Operating System :: OS Independent
Classifier: Programming Language :: Python
Classifier: Programming Language :: Python :: 3
Classifier: Programming Language :: Python :: 3.10
Classifier: Programming Language :: Python :: 3.11
Classifier: Programming Language :: Python :: 3.12
Classifier: Programming Language :: Python :: 3.13
Classifier: Topic :: Multimedia :: Video
Classifier: Topic :: Multimedia :: Sound/Audio
Classifier: Topic :: Software Development :: Libraries :: Python Modules
Classifier: Topic :: Software Development :: Libraries
Classifier: Topic :: Software Development :: Libraries :: Application Frameworks
Requires-Python: >=3.10
License-File: LICENSE
Provides-Extra: graph
Requires-Dist: graphviz; extra == "graph"
Dynamic: license-file
